MANIFEST.in
README.rst
requirements.txt
setup.cfg
setup.py
ARSpy.egg-info/PKG-INFO
ARSpy.egg-info/SOURCES.txt
ARSpy.egg-info/dependency_links.txt
ARSpy.egg-info/requires.txt
ARSpy.egg-info/top_level.txt
arspy/__init__.py
arspy/ars.py
arspy/hull.py
arspy/probability_utils.py
arspy/tests/__init__.py
arspy/tests/test_ars.py
arspy/tests/test_compute_hulls.py
arspy/tests/test_compute_segment_prob.py
arspy/tests/test_evaluate_hulls.py
docs/Makefile
docs/requirements-docs.txt
docs/source/api.rst
docs/source/conf.py
docs/source/index.rst
docs/source/api/ars.rst
docs/source/api/hull.rst