Metadata-Version: 1.1
Name: ARSpy
Version: 0.4
Summary: ARSpy
Home-page: https://github.com/MFreidank/ARSpy
Author: Moritz Freidank
Author-email: freidankm@googlemail.com
License: UNKNOWN
Download-URL: https://github.com/MFreidank/ARSpy/archive/0.4.tar.gz
Platform: UNKNOWN
